Workbook

Sheet Endgame Calculator
B1: SPARK Endgame Calculator
B2: Start with the life. Then engineer the business.
B3: Fill in the pink cells. Everything else works itself out. The numbers already in there are an example, so type over them.
B5: STEP 1 · RUN YOUR NUMBER: YOUR ENDGAME NUMBER
B6: What your Endgame life costs a year | C6: 150000 | D6: The life you want, from your Dream Life P&L. Rough is fine.
B7: Withdrawal rate | C7: 0.04 | D7: How much you take out each year. At 4%, your number is 25 times your life (1 ÷ 4% = 25).
B8: Your Endgame Number | C8: =IFERROR(C6/C7,0) -> 3750000 | D8: The invested wealth, outside your business, that makes working optional.
B10: STEP 2 · YOUR PATH: WHAT YOU NEED TO INVEST EACH YEAR
B11: Invested today, outside your business | C11: 100000 | D11: Shares, investment property equity, super, savings.
B12: Years until work is optional | C12: 15 | D12: When do you want working to become a choice?
B13: Expected growth rate | C13: 0.08 | D13: Be conservative. Returns aren't guaranteed and some years go backwards. Subtract inflation to keep everything in today's dollars.
B14: What you have today grows to | C14: =C11*(1+C13)^C12 -> 317216.91 | D14: If you didn't add another dollar.
B15: Where you are today | C15: =IFERROR(C11/C8,0) -> 0.026666667 | D15: What you have invested now, as a share of your Endgame Number.
B16: Invest each year | C16: =IFERROR(IF(C8-C14<=0,0,IF(C13>0,(C8-C14)*C13/((1+C13)^C12-1),(C8-C14)/C12)),0) -> 126427.84 | D16: What to put away each year, outside your business, to reach your number in time. Zero means you're already on track.
B17: Invest each month (approx.) | C17: =C16/12 -> 10535.653
B19: STEP 3 · ARCHITECT THE BUSINESS: YOUR CEO NUMBERS
B20: What your life costs today | C20: 100000 | D20: Not your Endgame life, the one you're living now.
B21: What you'll invest each year | C21: =C16 -> 126427.84 | D21: Pulled from step 2. Type over it to try a different amount.
B22: Annual business expenses | C22: 150000 | D22: What it costs to run your business.
B23: Profit buffer | C23: 0.2 | D23: Extra room for reinvestment, tax or safety.
B24: Weeks off per year | C24: 8
B25: Hours per week | C25: 25
B26: Price of your main offer | C26: 999
B28: What your business needs to pay you | C28: =C20+C21 -> 226427.84 | D28: What your life costs today, plus what you invest each year. Before tax. This is your real target, not revenue.
B29: Revenue needed a year | C29: =IFERROR((C28+C22)/(1-C23),0) -> 470534.8
B30: Revenue a month | C30: =C29/12 -> 39211.233
B31: Working weeks a year | C31: =52-C24 -> 44
B32: Revenue a working week | C32: =IFERROR(C29/C31,0) -> 10693.973
B33: Your time is worth, per hour | C33: =IFERROR(C32/C25,0) -> 427.75891
B34: Sales of your main offer a year | C34: =IFERROR(C29/C26,0) -> 471.0058
B35: Sales a month | C35: =C34/12 -> 39.250484
B36: Sales a week | C36: =IFERROR(C34/C31,0) -> 10.704677
B38: Your business is not the Endgame. It's the vehicle.
B40: A simple planning tool only. Not financial, tax or investment advice. Speak to a qualified accountant or financial adviser before making investment decisions.
B42: Want help with your numbers? My Endgame Session
B43: Ready to build it? Join the SPARK CEO Hub
B45: Now track it. Use the Monthly Check-in and Quarterly Check-in tabs as part of your CEO Rhythm.

Sheet Monthly Check-in
B1: MONTHLY CHECK-IN · ALIGNMENT
B2: Your DREAM sets the destination. Your CEO Rhythm keeps you on the road.
B3: At your monthly CEO check-in, log what you actually invested outside your business this month. It's the simplest question in your whole plan: did I invest my number? Fill in the pink cells only.
B5: Your monthly investment target | D5: ='Endgame Calculator'!C21/12 -> 10535.653 | E5: What you'll invest each year (calculator, step 3) divided by 12.
B6: The month you're starting | D6: 46296 | E6: Change this to your first month.
B8: Month | C8: Invested this month | D8: Target | E8: Difference | F8: Status | G8: Invested so far
B9: =D6 -> 46296 | D9: =$D$5 -> 10535.653 | E9: =IF(C9="","",C9-D9) | F9: =IF(C9="","",IF(C9>=D9,"On track","Catch up next month")) | G9: =IF(C9="","",SUM($C$9:C9))
B10: =EDATE(B9,1) -> 46327 | D10: =$D$5 -> 10535.653 | E10: =IF(C10="","",C10-D10) | F10: =IF(C10="","",IF(C10>=D10,"On track","Catch up next month")) | G10: =IF(C10="","",SUM($C$9:C10))
B11: =EDATE(B10,1) -> 46357 | D11: =$D$5 -> 10535.653 | E11: =IF(C11="","",C11-D11) | F11: =IF(C11="","",IF(C11>=D11,"On track","Catch up next month")) | G11: =IF(C11="","",SUM($C$9:C11))
B12: =EDATE(B11,1) -> 46388 | D12: =$D$5 -> 10535.653 | E12: =IF(C12="","",C12-D12) | F12: =IF(C12="","",IF(C12>=D12,"On track","Catch up next month")) | G12: =IF(C12="","",SUM($C$9:C12))
B13: =EDATE(B12,1) -> 46419 | D13: =$D$5 -> 10535.653 | E13: =IF(C13="","",C13-D13) | F13: =IF(C13="","",IF(C13>=D13,"On track","Catch up next month")) | G13: =IF(C13="","",SUM($C$9:C13))
B14: =EDATE(B13,1) -> 46447 | D14: =$D$5 -> 10535.653 | E14: =IF(C14="","",C14-D14) | F14: =IF(C14="","",IF(C14>=D14,"On track","Catch up next month")) | G14: =IF(C14="","",SUM($C$9:C14))
B15: =EDATE(B14,1) -> 46478 | D15: =$D$5 -> 10535.653 | E15: =IF(C15="","",C15-D15) | F15: =IF(C15="","",IF(C15>=D15,"On track","Catch up next month")) | G15: =IF(C15="","",SUM($C$9:C15))
B16: =EDATE(B15,1) -> 46508 | D16: =$D$5 -> 10535.653 | E16: =IF(C16="","",C16-D16) | F16: =IF(C16="","",IF(C16>=D16,"On track","Catch up next month")) | G16: =IF(C16="","",SUM($C$9:C16))
B17: =EDATE(B16,1) -> 46539 | D17: =$D$5 -> 10535.653 | E17: =IF(C17="","",C17-D17) | F17: =IF(C17="","",IF(C17>=D17,"On track","Catch up next month")) | G17: =IF(C17="","",SUM($C$9:C17))
B18: =EDATE(B17,1) -> 46569 | D18: =$D$5 -> 10535.653 | E18: =IF(C18="","",C18-D18) | F18: =IF(C18="","",IF(C18>=D18,"On track","Catch up next month")) | G18: =IF(C18="","",SUM($C$9:C18))
B19: =EDATE(B18,1) -> 46600 | D19: =$D$5 -> 10535.653 | E19: =IF(C19="","",C19-D19) | F19: =IF(C19="","",IF(C19>=D19,"On track","Catch up next month")) | G19: =IF(C19="","",SUM($C$9:C19))
B20: =EDATE(B19,1) -> 46631 | D20: =$D$5 -> 10535.653 | E20: =IF(C20="","",C20-D20) | F20: =IF(C20="","",IF(C20>=D20,"On track","Catch up next month")) | G20: =IF(C20="","",SUM($C$9:C20))
B21: =EDATE(B20,1) -> 46661 | D21: =$D$5 -> 10535.653 | E21: =IF(C21="","",C21-D21) | F21: =IF(C21="","",IF(C21>=D21,"On track","Catch up next month")) | G21: =IF(C21="","",SUM($C$9:C21))
... B44: =EDATE(B43,1) -> 47362 | D44: =$D$5 -> 10535.653 | E44: =IF(C44="","",C44-D44) | F44: =IF(C44="","",IF(C44>=D44,"On track","Catch up next month")) | G44: =IF(C44="","",SUM($C$9:C44))
B46: Need more months? Copy the last row down.

Sheet Quarterly Check-in
B1: QUARTERLY CHECK-IN · DIRECTION
B2: Where am I going, and am I still heading there?
B3: At your quarterly planning, add up everything you have invested outside your business: shares, investment property equity, super, savings. See how far you've come and whether you're ahead of your path. Then ask if your Endgame is still the one you want. You're allowed to change your mind.
B5: Your Endgame Number | D5: ='Endgame Calculator'!C8 -> 3750000 | E5: From the calculator, step 1.
B6: Invested when you started | D6: ='Endgame Calculator'!C11 -> 100000 | E6: From the calculator, step 2.
B7: What you'll invest each year | D7: ='Endgame Calculator'!C21 -> 126427.84 | E7: From the calculator, step 3.
B8: Expected growth rate | D8: ='Endgame Calculator'!C13 -> 0.08 | E8: From the calculator, step 2.
B9: Starting quarter | D9: ='Monthly Check-in'!D6 -> 46296 | E9: Set on the Monthly Check-in tab.
B11: Quarter | C11: Total invested now | D11: % of your number | E11: Your plan says | F11: Ahead / behind | G11: Progress to your Endgame
B12: =D9 -> 46296 | C12: =D6 -> 100000 | D12: =IF(C12="","",IFERROR(C12/$D$5,0)) -> 0.026666667 | E12: =IFERROR($D$6*(1+$D$8)^((ROW()-ROW($B$12))/4)+$D$7*((1+$D$8)^((ROW()-ROW($B$12))/4)-1)/$D$8,$D$6+$D$7*((ROW()-ROW($B$12))/4)) -> 100000 | F12: =IF(C12="","",C12-E12) -> 0 | G12: =IF(C12="","",REPT("■",ROUND(MIN(D12,1)*20,0))&REPT("□",20-ROUND(MIN(D12,1)*20,0))) -> ■□□□□□□□□□□□□□□□□□□□
B13: =EDATE(B12,3) -> 46388 | D13: =IF(C13="","",IFERROR(C13/$D$5,0)) | E13: =IFERROR($D$6*(1+$D$8)^((ROW()-ROW($B$12))/4)+$D$7*((1+$D$8)^((ROW()-ROW($B$12))/4)-1)/$D$8,$D$6+$D$7*((ROW()-ROW($B$12))/4)) -> 132643.36 | F13: =IF(C13="","",C13-E13) | G13: =IF(C13="","",REPT("■",ROUND(MIN(D13,1)*20,0))&REPT("□",20-ROUND(MIN(D13,1)*20,0)))
B14: =EDATE(B13,3) -> 46478 | D14: =IF(C14="","",IFERROR(C14/$D$5,0)) | E14: =IFERROR($D$6*(1+$D$8)^((ROW()-ROW($B$12))/4)+$D$7*((1+$D$8)^((ROW()-ROW($B$12))/4)-1)/$D$8,$D$6+$D$7*((ROW()-ROW($B$12))/4)) -> 165920.87 | F14: =IF(C14="","",C14-E14) | G14: =IF(C14="","",REPT("■",ROUND(MIN(D14,1)*20,0))&REPT("□",20-ROUND(MIN(D14,1)*20,0)))
B15: =EDATE(B14,3) -> 46569 | D15: =IF(C15="","",IFERROR(C15/$D$5,0)) | E15: =IFERROR($D$6*(1+$D$8)^((ROW()-ROW($B$12))/4)+$D$7*((1+$D$8)^((ROW()-ROW($B$12))/4)-1)/$D$8,$D$6+$D$7*((ROW()-ROW($B$12))/4)) -> 199844.84 | F15: =IF(C15="","",C15-E15) | G15: =IF(C15="","",REPT("■",ROUND(MIN(D15,1)*20,0))&REPT("□",20-ROUND(MIN(D15,1)*20,0)))
B16: =EDATE(B15,3) -> 46661 | D16: =IF(C16="","",IFERROR(C16/$D$5,0)) | E16: =IFERROR($D$6*(1+$D$8)^((ROW()-ROW($B$12))/4)+$D$7*((1+$D$8)^((ROW()-ROW($B$12))/4)-1)/$D$8,$D$6+$D$7*((ROW()-ROW($B$12))/4)) -> 234427.84 | F16: =IF(C16="","",C16-E16) | G16: =IF(C16="","",REPT("■",ROUND(MIN(D16,1)*20,0))&REPT("□",20-ROUND(MIN(D16,1)*20,0)))
B17: =EDATE(B16,3) -> 46753 | D17: =IF(C17="","",IFERROR(C17/$D$5,0)) | E17: =IFERROR($D$6*(1+$D$8)^((ROW()-ROW($B$12))/4)+$D$7*((1+$D$8)^((ROW()-ROW($B$12))/4)-1)/$D$8,$D$6+$D$7*((ROW()-ROW($B$12))/4)) -> 269682.67 | F17: =IF(C17="","",C17-E17) | G17: =IF(C17="","",REPT("■",ROUND(MIN(D17,1)*20,0))&REPT("□",20-ROUND(MIN(D17,1)*20,0)))
B18: =EDATE(B17,3) -> 46844 | D18: =IF(C18="","",IFERROR(C18/$D$5,0)) | E18: =IFERROR($D$6*(1+$D$8)^((ROW()-ROW($B$12))/4)+$D$7*((1+$D$8)^((ROW()-ROW($B$12))/4)-1)/$D$8,$D$6+$D$7*((ROW()-ROW($B$12))/4)) -> 305622.37 | F18: =IF(C18="","",C18-E18) | G18: =IF(C18="","",REPT("■",ROUND(MIN(D18,1)*20,0))&REPT("□",20-ROUND(MIN(D18,1)*20,0)))
B19: =EDATE(B18,3) -> 46935 | D19: =IF(C19="","",IFERROR(C19/$D$5,0)) | E19: =IFERROR($D$6*(1+$D$8)^((ROW()-ROW($B$12))/4)+$D$7*((1+$D$8)^((ROW()-ROW($B$12))/4)-1)/$D$8,$D$6+$D$7*((ROW()-ROW($B$12))/4)) -> 342260.27 | F19: =IF(C19="","",C19-E19) | G19: =IF(C19="","",REPT("■",ROUND(MIN(D19,1)*20,0))&REPT("□",20-ROUND(MIN(D19,1)*20,0)))
B20: =EDATE(B19,3) -> 47027 | D20: =IF(C20="","",IFERROR(C20/$D$5,0)) | E20: =IFERROR($D$6*(1+$D$8)^((ROW()-ROW($B$12))/4)+$D$7*((1+$D$8)^((ROW()-ROW($B$12))/4)-1)/$D$8,$D$6+$D$7*((ROW()-ROW($B$12))/4)) -> 379609.91 | F20: =IF(C20="","",C20-E20) | G20: =IF(C20="","",REPT("■",ROUND(MIN(D20,1)*20,0))&REPT("□",20-ROUND(MIN(D20,1)*20,0)))
B21: =EDATE(B20,3) -> 47119 | D21: =IF(C21="","",IFERROR(C21/$D$5,0)) | E21: =IFERROR($D$6*(1+$D$8)^((ROW()-ROW($B$12))/4)+$D$7*((1+$D$8)^((ROW()-ROW($B$12))/4)-1)/$D$8,$D$6+$D$7*((ROW()-ROW($B$12))/4)) -> 417685.12 | F21: =IF(C21="","",C21-E21) | G21: =IF(C21="","",REPT("■",ROUND(MIN(D21,1)*20,0))&REPT("□",20-ROUND(MIN(D21,1)*20,0)))
B22: =EDATE(B21,3) -> 47209 | D22: =IF(C22="","",IFERROR(C22/$D$5,0)) | E22: =IFERROR($D$6*(1+$D$8)^((ROW()-ROW($B$12))/4)+$D$7*((1+$D$8)^((ROW()-ROW($B$12))/4)-1)/$D$8,$D$6+$D$7*((ROW()-ROW($B$12))/4)) -> 456500 | F22: =IF(C22="","",C22-E22) | G22: =IF(C22="","",REPT("■",ROUND(MIN(D22,1)*20,0))&REPT("□",20-ROUND(MIN(D22,1)*20,0)))
B23: =EDATE(B22,3) -> 47300 | D23: =IF(C23="","",IFERROR(C23/$D$5,0)) | E23: =IFERROR($D$6*(1+$D$8)^((ROW()-ROW($B$12))/4)+$D$7*((1+$D$8)^((ROW()-ROW($B$12))/4)-1)/$D$8,$D$6+$D$7*((ROW()-ROW($B$12))/4)) -> 496068.93 | F23: =IF(C23="","",C23-E23) | G23: =IF(C23="","",REPT("■",ROUND(MIN(D23,1)*20,0))&REPT("□",20-ROUND(MIN(D23,1)*20,0)))
B24: =EDATE(B23,3) -> 47392 | D24: =IF(C24="","",IFERROR(C24/$D$5,0)) | E24: =IFERROR($D$6*(1+$D$8)^((ROW()-ROW($B$12))/4)+$D$7*((1+$D$8)^((ROW()-ROW($B$12))/4)-1)/$D$8,$D$6+$D$7*((ROW()-ROW($B$12))/4)) -> 536406.54 | F24: =IF(C24="","",C24-E24) | G24: =IF(C24="","",REPT("■",ROUND(MIN(D24,1)*20,0))&REPT("□",20-ROUND(MIN(D24,1)*20,0)))
... B72: =EDATE(B71,3) -> 51775 | D72: =IF(C72="","",IFERROR(C72/$D$5,0)) | E72: =IFERROR($D$6*(1+$D$8)^((ROW()-ROW($B$12))/4)+$D$7*((1+$D$8)^((ROW()-ROW($B$12))/4)-1)/$D$8,$D$6+$D$7*((ROW()-ROW($B$12))/4)) -> 3750000 | F72: =IF(C72="","",C72-E72) | G72: =IF(C72="","",REPT("■",ROUND(MIN(D72,1)*20,0))&REPT("□",20-ROUND(MIN(D72,1)*20,0)))
B74: Your plan says: roughly where your investments would be if you invest your yearly amount and get your expected growth rate. Not a promise. A planning tool only, not financial advice.
